<?xml version="1.0" encoding="UTF-8"?>
<!-- Created with TexturePacker http://www.codeandweb.com/texturepacker-->
<!-- $TexturePacker:SmartUpdate:3bd15504d282065ded7f1391855f872b:f75683b3346ff70356a0b8e186faa0a7:630bf85c9d1c7884fc2edb15bd4323b4$ -->
<TextureAtlas imagePath="memory_cards16.png" width="1671" height="254">
    <SubTexture name="clothes_card_16_0" x="183" y="146" rotated="true" width="160" height="101" frameX="-27" frameY="-13" frameWidth="173" frameHeight="173"/>
    <SubTexture name="clothes_card_16_1" x="1105" y="109" width="125" height="127" frameX="-15" frameY="-32" frameWidth="173" frameHeight="173"/>
    <SubTexture name="clothes_card_16_10" x="4" y="4" width="150" height="156" frameX="-3" frameY="-11" frameWidth="173" frameHeight="173"/>
    <SubTexture name="clothes_card_16_2" x="656" y="4" width="150" height="106" frameX="-1" frameY="-46" frameWidth="173" frameHeight="173"/>
    <SubTexture name="clothes_card_16_3" x="812" y="4" rotated="true" width="152" height="103" frameX="-26" frameY="-20" frameWidth="173" frameHeight="173"/>
    <SubTexture name="clothes_card_16_4" x="970" y="4" rotated="true" width="156" height="99" frameX="-28" frameY="-17" frameWidth="173" frameHeight="173"/>
    <SubTexture name="clothes_card_16_5" x="1471" y="76" width="99" height="125" frameX="-28" frameY="-34" frameWidth="173" frameHeight="173"/>
    <SubTexture name="clothes_card_16_6" x="1132" y="4" width="149" height="93" frameX="-3" frameY="-42" frameWidth="173" frameHeight="173"/>
    <SubTexture name="clothes_card_16_7" x="327" y="4" rotated="true" width="162" height="126" frameX="-15" frameY="-11" frameWidth="173" frameHeight="173"/>
    <SubTexture name="clothes_card_16_8" x="819" y="113" rotated="true" width="144" height="124" frameX="-15" frameY="-24" frameWidth="173" frameHeight="173"/>
    <SubTexture name="clothes_card_16_9" x="349" y="136" rotated="true" width="152" height="106" frameX="-24" frameY="-20" frameWidth="173" frameHeight="173"/>
    <SubTexture name="furniture_card_16_0" x="667" y="116" width="146" height="134" frameX="-5" frameY="-29" frameWidth="173" frameHeight="173"/>
    <SubTexture name="furniture_card_16_1" x="969" y="113" width="130" height="132" frameX="-13" frameY="-30" frameWidth="173" frameHeight="173"/>
    <SubTexture name="furniture_card_16_10" x="1287" y="4" rotated="true" width="165" height="72" frameX="-39" frameY="-8" frameWidth="173" frameHeight="173"/>
    <SubTexture name="furniture_card_16_2" x="1363" y="82" width="102" height="139" frameX="-27" frameY="-26" frameWidth="173" frameHeight="173"/>
    <SubTexture name="furniture_card_16_3" x="1236" y="103" rotated="true" width="121" height="131" frameX="-12" frameY="-35" frameWidth="173" frameHeight="173"/>
    <SubTexture name="furniture_card_16_4" x="4" y="166" width="173" height="72" frameX="0" frameY="-59" frameWidth="173" frameHeight="173"/>
    <SubTexture name="furniture_card_16_5" x="160" y="4" width="161" height="136" frameX="0" frameY="0" frameWidth="173" frameHeight="173"/>
    <SubTexture name="furniture_card_16_6" x="1576" y="76" width="65" height="156" frameX="-45" frameY="-17" frameWidth="173" frameHeight="173"/>
    <SubTexture name="furniture_card_16_7" x="507" y="130" rotated="true" width="154" height="120" frameX="-18" frameY="-19" frameWidth="173" frameHeight="173"/>
    <SubTexture name="furniture_card_16_8" x="1458" y="4" rotated="true" width="162" height="66" frameX="-45" frameY="-11" frameWidth="173" frameHeight="173"/>
    <SubTexture name="furniture_card_16_9" x="495" y="4" rotated="true" width="155" height="120" frameX="-18" frameY="-18" frameWidth="173" frameHeight="173"/>
</TextureAtlas>
